Metadata-Version: 2.4
Name: sheep-herding-rl
Version: 1.0.3
Summary: A reinforcement learning environment for sheep herding simulation with PPO, SAC, and TD3 algorithms
Home-page: https://github.com/dzijo/ferit-hackathon
Author: ferip
License: MIT
Project-URL: Homepage, https://github.com/dzijo/ferit-hackathon
Project-URL: Documentation, https://github.com/dzijo/ferit-hackathon
Project-URL: Repository, https://github.com/dzijo/ferit-hackathon
Project-URL: Bug Tracker, https://github.com/dzijo/ferit-hackathon/issues
Keywords: reinforcement-learning,simulation,ppo,sac,td3,sheep-herding
Classifier: Development Status :: 3 - Alpha
Classifier: Intended Audience :: Science/Research
Classifier: Intended Audience :: Developers
Classifier: Topic :: Scientific/Engineering :: Artificial Intelligence
Classifier: License :: OSI Approved :: MIT License
Classifier: Programming Language :: Python :: 3
Classifier: Programming Language :: Python :: 3.8
Classifier: Programming Language :: Python :: 3.9
Classifier: Programming Language :: Python :: 3.10
Classifier: Programming Language :: Python :: 3.11
Requires-Python: >=3.8
License-File: LICENSE
Requires-Dist: pygame
Requires-Dist: numpy
Requires-Dist: pillow
Requires-Dist: scipy
Requires-Dist: pyyaml
Requires-Dist: matplotlib
Requires-Dist: torch>=2.0.0
Provides-Extra: dev
Requires-Dist: pytest>=7.0; extra == "dev"
Requires-Dist: pytest-cov; extra == "dev"
Requires-Dist: black; extra == "dev"
Requires-Dist: flake8; extra == "dev"
Requires-Dist: mypy; extra == "dev"
Dynamic: home-page
Dynamic: license-file
Dynamic: requires-python
